nonpseudorandom/__init__.py
nonpseudorandom/_sensors.py
nonpseudorandom/nonpseudorandom.py
tests/__init__.py
tests/test_nonpseudorandom.py
nonpseudorandom-0.3.0.dist-info/LICENSE
nonpseudorandom-0.3.0.dist-info/METADATA
nonpseudorandom-0.3.0.dist-info/WHEEL
nonpseudorandom-0.3.0.dist-info/top_level.txt
nonpseudorandom-0.3.0.dist-info/RECORD
