Metadata-Version: 2.1
Name: nonpseudorandom
Version: 0.3.0
Summary: A true random number generator using system sensor noise
Home-page: https://github.com/Sven-J-Steinert/nonpseudorandom
Author: Sven Steinert
Author-email: sven.julius.steinert@outlook.com
Classifier: Programming Language :: Python :: 3 :: Only
Classifier: Programming Language :: Python :: 3.8
Classifier: Programming Language :: Python :: 3.9
Classifier: Programming Language :: Python :: 3.10
Classifier: Programming Language :: Python :: 3.11
Classifier: Programming Language :: Python :: 3.12
Classifier: License :: OSI Approved :: MIT License
Classifier: Operating System :: OS Independent
Requires-Python: >=3.6
License-File: LICENSE
Requires-Dist: psutil
Requires-Dist: numpy
Requires-Dist: sounddevice
Requires-Dist: opencv-python
